{
"meta":{"test_sets":[],"test_metrics":[],"learn_metrics":[{"best_value":"Min","name":"RMSE"}],"launch_mode":"Train","parameters":"","iteration_count":100,"learn_sets":["learn"],"name":"experiment"},
"iterations":[
{"learn":[14.005006],"iteration":0,"passed_time":0.0008731288304,"remaining_time":0.08643975421},
{"learn":[13.14441192],"iteration":1,"passed_time":0.001540503825,"remaining_time":0.07548468742},
{"learn":[12.34258257],"iteration":2,"passed_time":0.002182551571,"remaining_time":0.07056916747},
{"learn":[11.64527793],"iteration":3,"passed_time":0.002667696614,"remaining_time":0.06402471874},
{"learn":[11.02766183],"iteration":4,"passed_time":0.00332878989,"remaining_time":0.06324700791},
{"learn":[10.43485794],"iteration":5,"passed_time":0.004039285326,"remaining_time":0.06328213678},
{"learn":[9.890641275],"iteration":6,"passed_time":0.004886786348,"remaining_time":0.06492444719},
{"learn":[9.492161212],"iteration":7,"passed_time":0.005524976898,"remaining_time":0.06353723433},
{"learn":[9.105082953],"iteration":8,"passed_time":0.006165922589,"remaining_time":0.0623443284},
{"learn":[8.674157135],"iteration":9,"passed_time":0.006817878819,"remaining_time":0.06136090938},
{"learn":[8.341743544],"iteration":10,"passed_time":0.007524116312,"remaining_time":0.06087694107},
{"learn":[8.049372916],"iteration":11,"passed_time":0.008222248685,"remaining_time":0.06029649036},
{"learn":[7.757318612],"iteration":12,"passed_time":0.008947702025,"remaining_time":0.05988077509},
{"learn":[7.522206899],"iteration":13,"passed_time":0.009614195375,"remaining_time":0.05905862873},
{"learn":[7.297756655],"iteration":14,"passed_time":0.01034581021,"remaining_time":0.05862625786},
{"learn":[7.088359431],"iteration":15,"passed_time":0.0110265301,"remaining_time":0.05788928302},
{"learn":[6.882113791],"iteration":16,"passed_time":0.01171793993,"remaining_time":0.05721111849},
{"learn":[6.704728832],"iteration":17,"passed_time":0.0130384734,"remaining_time":0.05939748993},
{"learn":[6.563881962],"iteration":18,"passed_time":0.01368760436,"remaining_time":0.05835241859},
{"learn":[6.418790279],"iteration":19,"passed_time":0.01437068866,"remaining_time":0.05748275464},
{"learn":[6.315756953],"iteration":20,"passed_time":0.01503534859,"remaining_time":0.05656154946},
{"learn":[6.210157751],"iteration":21,"passed_time":0.01573949218,"remaining_time":0.05580365408},
{"learn":[6.115058449],"iteration":22,"passed_time":0.01639250037,"remaining_time":0.05487924037},
{"learn":[6.014819884],"iteration":23,"passed_time":0.0170424729,"remaining_time":0.05396783085},
{"learn":[5.93117229],"iteration":24,"passed_time":0.017695431,"remaining_time":0.053086293},
{"learn":[5.844857622],"iteration":25,"passed_time":0.01839588771,"remaining_time":0.05235752655},
{"learn":[5.771145213],"iteration":26,"passed_time":0.01926297527,"remaining_time":0.05208137758},
{"learn":[5.704018229],"iteration":27,"passed_time":0.02006899891,"remaining_time":0.05160599721},
{"learn":[5.665806474],"iteration":28,"passed_time":0.0208079875,"remaining_time":0.05094369354},
{"learn":[5.616500369],"iteration":29,"passed_time":0.02152727935,"remaining_time":0.05023031848},
{"learn":[5.558023666],"iteration":30,"passed_time":0.022282919,"remaining_time":0.04959746488},
{"learn":[5.510080976],"iteration":31,"passed_time":0.02303757682,"remaining_time":0.04895485075},
{"learn":[5.468747792],"iteration":32,"passed_time":0.02382264137,"remaining_time":0.04836718096},
{"learn":[5.429275534],"iteration":33,"passed_time":0.02457029613,"remaining_time":0.04769528072},
{"learn":[5.402117324],"iteration":34,"passed_time":0.02536567992,"remaining_time":0.04710769129},
{"learn":[5.367635151],"iteration":35,"passed_time":0.02621493422,"remaining_time":0.04660432749},
{"learn":[5.345181232],"iteration":36,"passed_time":0.02701621902,"remaining_time":0.04600058914},
{"learn":[5.319151269],"iteration":37,"passed_time":0.02797244287,"remaining_time":0.04563924889},
{"learn":[5.296134146],"iteration":38,"passed_time":0.02881009551,"remaining_time":0.04506194427},
{"learn":[5.269629003],"iteration":39,"passed_time":0.02965714569,"remaining_time":0.04448571854},
{"learn":[5.251147059],"iteration":40,"passed_time":0.0304818041,"remaining_time":0.04386405956},
{"learn":[5.248003302],"iteration":41,"passed_time":0.03080860375,"remaining_time":0.0425452147},
{"learn":[5.232376509],"iteration":42,"passed_time":0.03151284752,"remaining_time":0.04177284439},
{"learn":[5.213524255],"iteration":43,"passed_time":0.03231728822,"remaining_time":0.04113109409},
{"learn":[5.189691584],"iteration":44,"passed_time":0.03303834335,"remaining_time":0.04038019743},
{"learn":[5.166052198],"iteration":45,"passed_time":0.0337216681,"remaining_time":0.03958630603},
{"learn":[5.140406659],"iteration":46,"passed_time":0.03442442911,"remaining_time":0.03881903708},
{"learn":[5.118929684],"iteration":47,"passed_time":0.03512687954,"remaining_time":0.0380541195},
{"learn":[5.108792602],"iteration":48,"passed_time":0.0357883936,"remaining_time":0.03724914436},
{"learn":[5.098141225],"iteration":49,"passed_time":0.03648623543,"remaining_time":0.03648623543},
{"learn":[5.085926393],"iteration":50,"passed_time":0.03717979928,"remaining_time":0.03572176793},
{"learn":[5.067816804],"iteration":51,"passed_time":0.03788190907,"remaining_time":0.03496791607},
{"learn":[5.049834901],"iteration":52,"passed_time":0.03857913976,"remaining_time":0.03421168998},
{"learn":[5.03838627],"iteration":53,"passed_time":0.0392957466,"remaining_time":0.03347415451},
{"learn":[5.033534248],"iteration":54,"passed_time":0.03971247401,"remaining_time":0.03249202419},
{"learn":[5.023726885],"iteration":55,"passed_time":0.04039377498,"remaining_time":0.03173796606},
{"learn":[5.01290392],"iteration":56,"passed_time":0.04108961307,"remaining_time":0.03099742741},
{"learn":[5.005569127],"iteration":57,"passed_time":0.04200147416,"remaining_time":0.0304148606},
{"learn":[4.989969032],"iteration":58,"passed_time":0.0427678839,"remaining_time":0.02972005492},
{"learn":[4.976762446],"iteration":59,"passed_time":0.04355792774,"remaining_time":0.02903861849},
{"learn":[4.967222715],"iteration":60,"passed_time":0.0444352544,"remaining_time":0.02840942494},
{"learn":[4.954407599],"iteration":61,"passed_time":0.04513541055,"remaining_time":0.02766363872},
{"learn":[4.942125056],"iteration":62,"passed_time":0.04584339129,"remaining_time":0.02692389647},
{"learn":[4.930230716],"iteration":63,"passed_time":0.04655115163,"remaining_time":0.02618502279},
{"learn":[4.921695642],"iteration":64,"passed_time":0.04727089431,"remaining_time":0.02545355848},
{"learn":[4.906405625],"iteration":65,"passed_time":0.0479458735,"remaining_time":0.02469938938},
{"learn":[4.894330248],"iteration":66,"passed_time":0.04862529095,"remaining_time":0.02394977017},
{"learn":[4.88211557],"iteration":67,"passed_time":0.04927272876,"remaining_time":0.02318716647},
{"learn":[4.877946398],"iteration":68,"passed_time":0.04994925081,"remaining_time":0.02244096776},
{"learn":[4.863182126],"iteration":69,"passed_time":0.05060597594,"remaining_time":0.0216882754},
{"learn":[4.84646533],"iteration":70,"passed_time":0.05129415976,"remaining_time":0.02095113567},
{"learn":[4.838014752],"iteration":71,"passed_time":0.05197713385,"remaining_time":0.02021332983},
{"learn":[4.82981137],"iteration":72,"passed_time":0.05264523019,"remaining_time":0.0194715235},
{"learn":[4.817094767],"iteration":73,"passed_time":0.05333678028,"remaining_time":0.01873994983},
{"learn":[4.808314151],"iteration":74,"passed_time":0.05398522997,"remaining_time":0.01799507666},
{"learn":[4.796235023],"iteration":75,"passed_time":0.05465290553,"remaining_time":0.01725881227},
{"learn":[4.784434534],"iteration":76,"passed_time":0.05531333757,"remaining_time":0.01652216577},
{"learn":[4.774402487],"iteration":77,"passed_time":0.05596783855,"remaining_time":0.01578580062},
{"learn":[4.76731896],"iteration":78,"passed_time":0.05665536113,"remaining_time":0.01506028587},
{"learn":[4.75934113],"iteration":79,"passed_time":0.05734756244,"remaining_time":0.01433689061},
{"learn":[4.754106378],"iteration":80,"passed_time":0.05805878924,"remaining_time":0.01361872834},
{"learn":[4.744002932],"iteration":81,"passed_time":0.0588296573,"remaining_time":0.01291382721},
{"learn":[4.731700554],"iteration":82,"passed_time":0.0597081862,"remaining_time":0.01222938754},
{"learn":[4.723284153],"iteration":83,"passed_time":0.06045076149,"remaining_time":0.01151443076},
{"learn":[4.712232782],"iteration":84,"passed_time":0.06118243643,"remaining_time":0.01079690055},
{"learn":[4.703046867],"iteration":85,"passed_time":0.0619064571,"remaining_time":0.01007779534},
{"learn":[4.698601855],"iteration":86,"passed_time":0.06268804516,"remaining_time":0.009367179162},
{"learn":[4.692429407],"iteration":87,"passed_time":0.0634413204,"remaining_time":0.008651089146},
{"learn":[4.675027364],"iteration":88,"passed_time":0.06417335602,"remaining_time":0.007931538385},
{"learn":[4.662368584],"iteration":89,"passed_time":0.06495211881,"remaining_time":0.00721690209},
{"learn":[4.646206172],"iteration":90,"passed_time":0.06580902738,"remaining_time":0.006508585126},
{"learn":[4.641245848],"iteration":91,"passed_time":0.06652393104,"remaining_time":0.005784689656},
{"learn":[4.633900435],"iteration":92,"passed_time":0.06729957802,"remaining_time":0.005065559636},
{"learn":[4.624738236],"iteration":93,"passed_time":0.06800497394,"remaining_time":0.004340743018},
{"learn":[4.612798287],"iteration":94,"passed_time":0.0686978465,"remaining_time":0.003615676132},
{"learn":[4.605222001],"iteration":95,"passed_time":0.06937273552,"remaining_time":0.002890530646},
{"learn":[4.601725912],"iteration":96,"passed_time":0.07004507978,"remaining_time":0.002166342674},
{"learn":[4.59722371],"iteration":97,"passed_time":0.07073022793,"remaining_time":0.001443474039},
{"learn":[4.580235665],"iteration":98,"passed_time":0.07140716076,"remaining_time":0.0007212844521},
{"learn":[4.57591791],"iteration":99,"passed_time":0.07206930599,"remaining_time":0}
]}